setup.cfg
setup.py
tests/__init__.py
tests/test_base.py
todoist/__init__.py
todoist/base.py
todoist/settings.py
todoist/utils.py
todoist.egg-info/PKG-INFO
todoist.egg-info/SOURCES.txt
todoist.egg-info/dependency_links.txt
todoist.egg-info/top_level.txt