Metadata-Version: 1.0
Name: todoist
Version: 0.0.1
Summary: todoist is a Python wrapper around the Todoist API
Home-page: http://todoist.com/API/
Author: Gökmen Görgen
Author-email: gokmen@alageek.com
License: GPLv3
Platform: UNKNOWN
